libfive/__init__.py
libfive/__init__.pyi
libfive/_libfive.pyx
libfive/py.typed
libfive/_libfive.cpython-38-x86_64-linux-gnu.so
libfive-0.1.0a3.dist-info/LICENSE.md
libfive-0.1.0a3.dist-info/WHEEL
libfive-0.1.0a3.dist-info/METADATA
libfive-0.1.0a3.dist-info/RECORD
